spiff_arena_common/__init__.py
spiff_arena_common/jinja.py
spiff_arena_common/py.typed
spiff_arena_common/runner.py
spiff_arena_common-0.1.5.dist-info/METADATA
spiff_arena_common-0.1.5.dist-info/WHEEL
spiff_arena_common-0.1.5.dist-info/RECORD
