Metadata-Version: 2.4
Name: spiff-arena-common
Version: 0.1.5
Summary: Shared Python utilities for Spiff Arena frontend and backend components
Requires-Python: <3.13,>=3.10
